astronomer_orbiter-1.10.5.dist-info/licenses/LICENSE
orbiter/__init__.py
orbiter/__main__.py
orbiter/ast_helper.py
orbiter/config.py
orbiter/default_translation.py
orbiter/file_types.py
orbiter/meta.py
orbiter/assets/__init__.py
orbiter/assets/supported_origins.csv
orbiter/assets/operators/__init__.py
orbiter/assets/operators/unmapped_src.py
orbiter/objects/__init__.py
orbiter/objects/airflow_settings.py
orbiter/objects/connection.py
orbiter/objects/dag.py
orbiter/objects/env_var.py
orbiter/objects/include.py
orbiter/objects/pool.py
orbiter/objects/project.py
orbiter/objects/requirement.py
orbiter/objects/task.py
orbiter/objects/task_group.py
orbiter/objects/task_shared_utils.py
orbiter/objects/tasks_parent_shared_utils.py
orbiter/objects/variable.py
orbiter/objects/callbacks/__init__.py
orbiter/objects/callbacks/callback_type.py
orbiter/objects/callbacks/smtp.py
orbiter/objects/operators/__init__.py
orbiter/objects/operators/bash.py
orbiter/objects/operators/empty.py
orbiter/objects/operators/kubernetes_pod.py
orbiter/objects/operators/livy.py
orbiter/objects/operators/python.py
orbiter/objects/operators/smtp.py
orbiter/objects/operators/sql.py
orbiter/objects/operators/ssh.py
orbiter/objects/operators/unmapped.py
orbiter/objects/operators/win_rm.py
orbiter/objects/timetables/__init__.py
orbiter/objects/timetables/multiple_cron_trigger_timetable.py
orbiter/objects/timetables/timetable.py
orbiter/rules/__init__.py
orbiter/rules/rulesets.py
astronomer_orbiter-1.10.5.dist-info/METADATA
astronomer_orbiter-1.10.5.dist-info/WHEEL
astronomer_orbiter-1.10.5.dist-info/entry_points.txt
astronomer_orbiter-1.10.5.dist-info/top_level.txt
astronomer_orbiter-1.10.5.dist-info/RECORD
