Metadata-Version: 2.4
Name: astronomer-orbiter
Version: 1.10.5
Summary: Astronomer Orbiter can take your legacy workloads and land them safely down in a new home on Apache Airflow!
Author-email: Fritz Davenport <fritz@astronomer.io>, Astronomer <humans@astronomer.io>
License:                                  Apache License
Project-URL: Homepage, https://astronomer.io
Project-URL: Source, https://github.com/astronomer/orbiter/
Requires-Python: >=3.10
License-File: LICENSE
Requires-Dist: click
Requires-Dist: rich-click
Requires-Dist: questionary
Requires-Dist: requests
Requires-Dist: pydantic>=2.6
Requires-Dist: pydantic-settings
Requires-Dist: pydantic-extra-types[pendulum]>=2.10.6
Requires-Dist: typing-extensions>=4.0.0; python_version < "3.11"
Requires-Dist: dill
Requires-Dist: inflection
Requires-Dist: jinja2
Requires-Dist: xmltodict
Requires-Dist: pyyaml
Requires-Dist: pendulum
Requires-Dist: tzdata
Requires-Dist: tabulate
Requires-Dist: loguru
Requires-Dist: ruff
Requires-Dist: eval_type_backport; python_version < "3.10"
Requires-Dist: mkdocs
Requires-Dist: mkdocs-material
Requires-Dist: pygments
Requires-Dist: mkdocstrings-python
Requires-Dist: htmlark
Provides-Extra: dev
Requires-Dist: build; extra == "dev"
Requires-Dist: twine>=4.0.2; extra == "dev"
Requires-Dist: pyinstaller; extra == "dev"
Requires-Dist: mkdocs; extra == "dev"
Requires-Dist: mkdocs-click; extra == "dev"
Requires-Dist: mkdocs-material; extra == "dev"
Requires-Dist: mkdocstrings~=0.30; extra == "dev"
Requires-Dist: mkdocstrings-python~=1.18; extra == "dev"
Requires-Dist: markdown-exec; extra == "dev"
Requires-Dist: pygments; extra == "dev"
Requires-Dist: griffe-inherited-docstrings; extra == "dev"
Requires-Dist: pytest>=7.4; extra == "dev"
Requires-Dist: pytest-cov>=4.1; extra == "dev"
Requires-Dist: pytest-sugar>=0.9.7; extra == "dev"
Requires-Dist: black>=23.12.0; extra == "dev"
Requires-Dist: ruff>=0.1.0; extra == "dev"
Requires-Dist: pylint>=3.0.0; extra == "dev"
Requires-Dist: isort>=5.13.0; extra == "dev"
Requires-Dist: pre-commit>=3.6.0; python_version >= "3.9" and extra == "dev"
Requires-Dist: detect-secrets>=1.4.0; extra == "dev"
Dynamic: license-file
